{
    "Entity": {
                "components": {
		    "EntityDescriptor": {
                        "children": [],
                        "name": "UI Object",
                        "parent": null,
                        "sceneID": 18446744073709551615
                    },
                    "GUIRenderer": {
                        "Color": {
                            "a": 1.0,
                            "b": 1.0,
                            "g": 1.0,
                            "r": 1.0
                        },
                        "TextureKey": ""
                    },
                    "Transform": {
                        "height": 250.0,
                        "orientation": 0.0,
                        "position": {
                            "x": 0.0,
                            "y": 0.0
                        },
                        "width": 250.0
                    }
                },
                "name": ""
            }
}